{
  "questionId": "q-13604",
  "questionType": "question",
  "totalEvents": 1,
  "latestEvent": {
    "eventType": "created",
    "createdAt": "2026-02-08T20:49:50.096Z"
  },
  "eventTypes": {
    "created": 1
  },
  "history": [
    {
      "eventType": "created",
      "eventSource": "system",
      "sourceName": "content-pipeline",
      "changesSummary": "Question added to linux-foundation-sysadmin channel",
      "changedFields": null,
      "reason": null,
      "metadata": null,
      "createdAt": "2026-02-08T20:49:50.096Z"
    }
  ]
}