{
  "questionId": "q-13865",
  "questionType": "question",
  "totalEvents": 1,
  "latestEvent": {
    "eventType": "created",
    "createdAt": "2026-02-09T16:10:54.374Z"
  },
  "eventTypes": {
    "created": 1
  },
  "history": [
    {
      "eventType": "created",
      "eventSource": "system",
      "sourceName": "content-pipeline",
      "changesSummary": "Question added to database channel",
      "changedFields": null,
      "reason": null,
      "metadata": null,
      "createdAt": "2026-02-09T16:10:54.374Z"
    }
  ]
}