{
  "questionId": "q-18730",
  "questionType": "question",
  "totalEvents": 1,
  "latestEvent": {
    "eventType": "created",
    "createdAt": "2026-02-21T17:47:58.915Z"
  },
  "eventTypes": {
    "created": 1
  },
  "history": [
    {
      "eventType": "created",
      "eventSource": "system",
      "sourceName": "content-pipeline",
      "changesSummary": "Question added to azure-ai-engineer channel",
      "changedFields": null,
      "reason": null,
      "metadata": null,
      "createdAt": "2026-02-21T17:47:58.915Z"
    }
  ]
}