{
  "questionId": "q-21291",
  "questionType": "question",
  "totalEvents": 1,
  "latestEvent": {
    "eventType": "created",
    "createdAt": "2026-03-03T21:49:38.082Z"
  },
  "eventTypes": {
    "created": 1
  },
  "history": [
    {
      "eventType": "created",
      "eventSource": "system",
      "sourceName": "content-pipeline",
      "changesSummary": "Question added to linux channel",
      "changedFields": null,
      "reason": null,
      "metadata": null,
      "createdAt": "2026-03-03T21:49:38.082Z"
    }
  ]
}