{
  "questionId": "q-24192",
  "questionType": "question",
  "totalEvents": 1,
  "latestEvent": {
    "eventType": "created",
    "createdAt": "2026-03-10T21:23:47.201Z"
  },
  "eventTypes": {
    "created": 1
  },
  "history": [
    {
      "eventType": "created",
      "eventSource": "system",
      "sourceName": "content-pipeline",
      "changesSummary": "Question added to machine-learning channel",
      "changedFields": null,
      "reason": null,
      "metadata": null,
      "createdAt": "2026-03-10T21:23:47.201Z"
    }
  ]
}