{
  "questionId": "q-2550",
  "questionType": "question",
  "totalEvents": 1,
  "latestEvent": {
    "eventType": "created",
    "createdAt": "2026-01-15T22:40:03.617Z"
  },
  "eventTypes": {
    "created": 1
  },
  "history": [
    {
      "eventType": "created",
      "eventSource": "system",
      "sourceName": "content-pipeline",
      "changesSummary": "Question added to azure-solutions-architect channel",
      "changedFields": null,
      "reason": null,
      "metadata": null,
      "createdAt": "2026-01-15T22:40:03.617Z"
    }
  ]
}