{
  "questionId": "q-27188",
  "questionType": "question",
  "totalEvents": 1,
  "latestEvent": {
    "eventType": "created",
    "createdAt": "2026-04-03T13:24:24.510Z"
  },
  "eventTypes": {
    "created": 1
  },
  "history": [
    {
      "eventType": "created",
      "eventSource": "system",
      "sourceName": "content-pipeline",
      "changesSummary": "Question added to performance-testing channel",
      "changedFields": null,
      "reason": null,
      "metadata": null,
      "createdAt": "2026-04-03T13:24:24.510Z"
    }
  ]
}