{
  "questionId": "q-29614",
  "questionType": "question",
  "totalEvents": 1,
  "latestEvent": {
    "eventType": "created",
    "createdAt": "2026-04-10T21:49:31.098Z"
  },
  "eventTypes": {
    "created": 1
  },
  "history": [
    {
      "eventType": "created",
      "eventSource": "system",
      "sourceName": "content-pipeline",
      "changesSummary": "Question added to gcp-cloud-architect channel",
      "changedFields": null,
      "reason": null,
      "metadata": null,
      "createdAt": "2026-04-10T21:49:31.098Z"
    }
  ]
}