{
  "questionId": "q-3031",
  "questionType": "question",
  "totalEvents": 1,
  "latestEvent": {
    "eventType": "created",
    "createdAt": "2026-01-16T21:46:35.529Z"
  },
  "eventTypes": {
    "created": 1
  },
  "history": [
    {
      "eventType": "created",
      "eventSource": "system",
      "sourceName": "content-pipeline",
      "changesSummary": "Question added to security channel",
      "changedFields": null,
      "reason": null,
      "metadata": null,
      "createdAt": "2026-01-16T21:46:35.529Z"
    }
  ]
}