{
  "questionId": "q-5216",
  "questionType": "question",
  "totalEvents": 1,
  "latestEvent": {
    "eventType": "created",
    "createdAt": "2026-01-21T11:01:47.136Z"
  },
  "eventTypes": {
    "created": 1
  },
  "history": [
    {
      "eventType": "created",
      "eventSource": "system",
      "sourceName": "content-pipeline",
      "changesSummary": "Question added to api-testing channel",
      "changedFields": null,
      "reason": null,
      "metadata": null,
      "createdAt": "2026-01-21T11:01:47.136Z"
    }
  ]
}