{
  "questionId": "q-6352",
  "questionType": "question",
  "totalEvents": 1,
  "latestEvent": {
    "eventType": "created",
    "createdAt": "2026-01-23T20:41:43.296Z"
  },
  "eventTypes": {
    "created": 1
  },
  "history": [
    {
      "eventType": "created",
      "eventSource": "system",
      "sourceName": "content-pipeline",
      "changesSummary": "Question added to aws-ai-practitioner channel",
      "changedFields": null,
      "reason": null,
      "metadata": null,
      "createdAt": "2026-01-23T20:41:43.296Z"
    }
  ]
}