{
  "questionId": "q-7251",
  "questionType": "question",
  "totalEvents": 1,
  "latestEvent": {
    "eventType": "created",
    "createdAt": "2026-01-25T15:31:51.490Z"
  },
  "eventTypes": {
    "created": 1
  },
  "history": [
    {
      "eventType": "created",
      "eventSource": "system",
      "sourceName": "content-pipeline",
      "changesSummary": "Question added to android channel",
      "changedFields": null,
      "reason": null,
      "metadata": null,
      "createdAt": "2026-01-25T15:31:51.490Z"
    }
  ]
}