{
  "questionId": "q-7673",
  "questionType": "question",
  "totalEvents": 1,
  "latestEvent": {
    "eventType": "created",
    "createdAt": "2026-01-26T12:03:17.817Z"
  },
  "eventTypes": {
    "created": 1
  },
  "history": [
    {
      "eventType": "created",
      "eventSource": "system",
      "sourceName": "content-pipeline",
      "changesSummary": "Question added to aws-security-specialty channel",
      "changedFields": null,
      "reason": null,
      "metadata": null,
      "createdAt": "2026-01-26T12:03:17.817Z"
    }
  ]
}