{
  "questionId": "q-7914",
  "questionType": "question",
  "totalEvents": 1,
  "latestEvent": {
    "eventType": "created",
    "createdAt": "2026-01-26T22:47:02.201Z"
  },
  "eventTypes": {
    "created": 1
  },
  "history": [
    {
      "eventType": "created",
      "eventSource": "system",
      "sourceName": "content-pipeline",
      "changesSummary": "Question added to sre channel",
      "changedFields": null,
      "reason": null,
      "metadata": null,
      "createdAt": "2026-01-26T22:47:02.201Z"
    }
  ]
}